ros2_pkg_create/__init__.py
ros2_pkg_create/__main__.py
ros2_pkg_create/copier.yml
ros2_pkg_create/templates/ros2_cpp_pkg/{% if has_action_server %}{{ package_name }}_interfaces{% endif %}/CMakeLists.txt.jinja
ros2_pkg_create/templates/ros2_cpp_pkg/{% if has_action_server %}{{ package_name }}_interfaces{% endif %}/README.md.jinja
ros2_pkg_create/templates/ros2_cpp_pkg/{% if has_action_server %}{{ package_name }}_interfaces{% endif %}/package.xml.jinja
ros2_pkg_create/templates/ros2_cpp_pkg/{% if has_action_server %}{{ package_name }}_interfaces{% endif %}/action/Fibonacci.action
ros2_pkg_create/templates/ros2_cpp_pkg/{{ package_name }}/CMakeLists.txt.jinja
ros2_pkg_create/templates/ros2_cpp_pkg/{{ package_name }}/README.md.jinja
ros2_pkg_create/templates/ros2_cpp_pkg/{{ package_name }}/package.xml.jinja
ros2_pkg_create/templates/ros2_cpp_pkg/{{ package_name }}/{% if has_docker_ros and docker_ros_type == 'gitlab' %}.gitlab-ci.yml{% endif %}.jinja
ros2_pkg_create/templates/ros2_cpp_pkg/{{ package_name }}/include/{{ package_name }}/{{ node_name }}.hpp.jinja
ros2_pkg_create/templates/ros2_cpp_pkg/{{ package_name }}/src/{{ node_name }}.cpp.jinja
ros2_pkg_create/templates/ros2_cpp_pkg/{{ package_name }}/{% if has_docker_ros and docker_ros_type == 'github' %}.github{% endif %}/workflows/docker-ros.yml.jinja
ros2_pkg_create/templates/ros2_cpp_pkg/{{ package_name }}/{% if has_launch_file %}launch{% endif %}/{% if launch_file_type == 'py' %}{{ node_name }}_launch.py{% endif %}.jinja
ros2_pkg_create/templates/ros2_cpp_pkg/{{ package_name }}/{% if has_launch_file %}launch{% endif %}/{% if launch_file_type == 'xml' %}{{ node_name }}_launch.xml{% endif %}.jinja
ros2_pkg_create/templates/ros2_cpp_pkg/{{ package_name }}/{% if has_launch_file %}launch{% endif %}/{% if launch_file_type == 'yml' %}{{ node_name }}_launch.yml{% endif %}.jinja
ros2_pkg_create/templates/ros2_cpp_pkg/{{ package_name }}/{% if has_params or has_diagnostics %}config{% endif %}/params.yml.jinja
ros2_pkg_create-1.3.0.dist-info/METADATA
ros2_pkg_create-1.3.0.dist-info/WHEEL
ros2_pkg_create-1.3.0.dist-info/entry_points.txt
ros2_pkg_create-1.3.0.dist-info/top_level.txt
ros2_pkg_create-1.3.0.dist-info/RECORD
