Metadata-Version: 2.4
Name: ros2-pkg-create
Version: 1.3.0
Summary: Powerful ROS 2 Package Generator
Author-email: Lennart Reiher <lennart.reiher@rwth-aachen.de>, Jean-Pierre Busch <jean-pierre.busch@rwth-aachen.de>
Maintainer-email: Lennart Reiher <lennart.reiher@rwth-aachen.de>, Jean-Pierre Busch <jean-pierre.busch@rwth-aachen.de>
Project-URL: Repository, https://github.com/ika-rwth-aachen/ros2-pkg-create
Project-URL: Bug Tracker, https://github.com/ika-rwth-aachen/ros2-pkg-create/issues
Keywords: ros,ros2
Classifier: License :: OSI Approved :: MIT License
Classifier: Programming Language :: Python
Classifier: Programming Language :: Python :: 3
Classifier: Operating System :: POSIX :: Linux
Requires-Python: >=3.7
Requires-Dist: argcomplete~=3.2.3
Requires-Dist: copier~=9.2.0
Requires-Dist: jinja2-strcase~=0.0.2
Provides-Extra: dev
Requires-Dist: build; extra == "dev"
Requires-Dist: twine; extra == "dev"
